docspec_python/__init__.py
docspec_python/__main__.py
docspec_python/parser.py
docspec_python/py.typed
docspec_python-2.2.0.dist-info/METADATA
docspec_python-2.2.0.dist-info/WHEEL
docspec_python-2.2.0.dist-info/entry_points.txt
docspec_python-2.2.0.dist-info/RECORD
