Metadata-Version: 2.1
Name: docspec-python
Version: 2.2.0
Summary: A parser based on lib2to3 producing docspec data from Python source code.
Home-page: https://github.com/NiklasRosenstein/docspec/
License: MIT
Author: Niklas Rosenstein
Author-email: rosensteinniklas@gmail.com
Requires-Python: >=3.7,<4.0
Classifier: License :: OSI Approved :: MIT License
Classifier: Programming Language :: Python :: 3
Classifier: Programming Language :: Python :: 3.7
Classifier: Programming Language :: Python :: 3.8
Classifier: Programming Language :: Python :: 3.9
Classifier: Programming Language :: Python :: 3.10
Classifier: Programming Language :: Python :: 3.11
Requires-Dist: black (>=23.1.0,<24.0.0)
Requires-Dist: docspec (>=2.2.0,<3.0.0)
Requires-Dist: nr.util (>=0.7.0)
